tabulargrpo/__init__.py
tabulargrpo/demo.py
tabulargrpo/inference.py
tabulargrpo/setup.py
tabulargrpo/tabulargrpo_classifier.py
tabulargrpo/models/__init__.py
tabulargrpo/models/transformer.py
tabulargrpo/models/transformer_lta.py
tabulargrpo/models/transformer_moe.py
tabulargrpo-0.1.3.dist-info/METADATA
tabulargrpo-0.1.3.dist-info/WHEEL
tabulargrpo-0.1.3.dist-info/top_level.txt
tabulargrpo-0.1.3.dist-info/RECORD
