Metadata-Version: 2.4
Name: tabulargrpo
Version: 0.1.3
Summary: A TabularGRPO classifier package
Home-page: https://github.com/enkhtogtokh/tabulargrpo
Author: Dr. Enkhtogtokh Togootogtokh
Author-email: enkhtogtokh.java@gmail.com
Classifier: Programming Language :: Python :: 3
Classifier: License :: OSI Approved :: MIT License
Classifier: Operating System :: OS Independent
Requires-Python: >=3.7
Requires-Dist: numpy
Requires-Dist: pandas
Requires-Dist: torch
Requires-Dist: scikit-learn
Dynamic: author
Dynamic: author-email
Dynamic: classifier
Dynamic: description
Dynamic: description-content-type
Dynamic: home-page
Dynamic: requires-dist
Dynamic: requires-python
Dynamic: summary
